covenance/__init__.py
covenance/_caller_context.py
covenance/_lazy_client.py
covenance/_version.py
covenance/client.py
covenance/dev_tools.py
covenance/exceptions.py
covenance/keys.py
covenance/pricing.py
covenance/record.py
covenance/response_adapter.py
covenance/retry.py
covenance/visual.py
covenance/clients/__init__.py
covenance/clients/anthropic_client.py
covenance/clients/google_client.py
covenance/clients/grok_client.py
covenance/clients/mistral_client.py
covenance/clients/openai_client.py
covenance/clients/openrouter_client.py
covenance/models/__init__.py
covenance/models/anthropic.py
covenance/models/google.py
covenance/models/grok.py
covenance/models/mistral.py
covenance/models/openai.py
covenance/models/openrouter.py
covenance-0.0.6.dist-info/METADATA
covenance-0.0.6.dist-info/WHEEL
covenance-0.0.6.dist-info/licenses/LICENSE
covenance-0.0.6.dist-info/RECORD
