Metadata-Version: 2.4
Name: covenance
Version: 0.0.6
Summary: Online LLM clients for OpenAI, Google Gemini, Mistral, Anthropic Claude, and OpenRouter
Author: Ilya Kamen
License: MIT
License-File: LICENSE
Keywords: anthropic,gemini,llm,mistral,openai,openrouter
Classifier: License :: OSI Approved :: MIT License
Classifier: Programming Language :: Python
Classifier: Programming Language :: Python :: 3
Classifier: Programming Language :: Python :: 3.10
Classifier: Programming Language :: Python :: 3.11
Classifier: Programming Language :: Python :: 3.12
Classifier: Programming Language :: Python :: 3.13
Classifier: Topic :: Software Development :: Libraries :: Python Modules
Classifier: Topic :: Utilities
Requires-Python: >=3.10
Requires-Dist: pydantic
Requires-Dist: python-dotenv
Provides-Extra: all
Requires-Dist: anthropic; extra == 'all'
Requires-Dist: google-genai; extra == 'all'
Requires-Dist: mistralai; extra == 'all'
Requires-Dist: openai; extra == 'all'
Provides-Extra: anthropic
Requires-Dist: anthropic; extra == 'anthropic'
Provides-Extra: dev
Requires-Dist: build; extra == 'dev'
Requires-Dist: pre-commit; extra == 'dev'
Requires-Dist: pytest; extra == 'dev'
Requires-Dist: pytest-cov; extra == 'dev'
Requires-Dist: pytest-rerunfailures; extra == 'dev'
Requires-Dist: pytest-xdist; extra == 'dev'
Requires-Dist: ruff; extra == 'dev'
Requires-Dist: twine; extra == 'dev'
Provides-Extra: google
Requires-Dist: google-genai; extra == 'google'
Provides-Extra: mistral
Requires-Dist: mistralai; extra == 'mistral'
Provides-Extra: openai
Requires-Dist: openai; extra == 'openai'
